init_python_project/__main__.py
init_python_project/cli.py
init_python_project/copier.yaml
init_python_project/template/.gitignore.jinja
init_python_project/template/CHANGELOG.md.jinja
init_python_project/template/Makefile.jinja
init_python_project/template/README.md.jinja
init_python_project/template/context
init_python_project/template/pyproject.toml.jinja
init_python_project/template/{% if bumpversion %}.bumpversion.cfg{% endif %}.jinja
init_python_project/template/{% if docs == 'mkdocs' %}mkdocs.yml{% endif %}.jinja
init_python_project/template/{% if precommit %}.pre-commit-config.yaml{% endif %}.jinja
init_python_project/template/{% if remote.startswith('gitlab') %}.gitlab-ci.yml{% endif %}.jinja
init_python_project/template/{{ _copier_conf.answers_file }}.jinja
init_python_project/template/src/{{package_name}}/__init__.py
init_python_project/template/src/{{package_name}}/__main__.py
init_python_project/template/src/{{package_name}}/cli.py.jinja
init_python_project/template/src/{{package_name}}/package_data.dat
init_python_project/template/src/{{package_name}}/simple.py
init_python_project/template/tests/test_cli.py.jinja
init_python_project/template/tests/test_simple.py.jinja
init_python_project/template/{% if docs == 'mkdocs' %}docs{% endif %}/index.md
init_python_project/template/{% if docs == 'mkdocs' %}docs{% endif %}/macros.py
init_python_project/template/{% if docs == 'mkdocs' %}docs{% endif %}/reference.md.jinja
init_python_project/template/{% if docs == 'mkdocs' %}docs{% endif %}/requirements.txt
init_python_project/template/{% if docs == 'sphinx' and docs_template=='none' %}docs{% endif %}/Makefile
init_python_project/template/{% if docs == 'sphinx' and docs_template=='none' %}docs{% endif %}/changelog.md
init_python_project/template/{% if docs == 'sphinx' and docs_template=='none' %}docs{% endif %}/conf.py.jinja
init_python_project/template/{% if docs == 'sphinx' and docs_template=='none' %}docs{% endif %}/index.md
init_python_project-0.0.6.dist-info/LICENSE
init_python_project-0.0.6.dist-info/METADATA
init_python_project-0.0.6.dist-info/WHEEL
init_python_project-0.0.6.dist-info/entry_points.txt
init_python_project-0.0.6.dist-info/top_level.txt
init_python_project-0.0.6.dist-info/RECORD
