Metadata-Version: 2.1
Name: init-python-project
Version: 0.0.6
Summary: A python project generator.
Author-email: Jannis Mainczyk <jmainczyk@gmail.com>
Maintainer-email: Jannis Mainczyk <jmainczyk@gmail.com>
License: The MIT License (MIT)
Requires-Python: >=3.11
License-File: LICENSE
Requires-Dist: copier
Requires-Dist: typer[all]
Provides-Extra: dev
Requires-Dist: black ; extra == 'dev'
Requires-Dist: pre-commit ; extra == 'dev'
Requires-Dist: ruff ; extra == 'dev'
Provides-Extra: doc
Requires-Dist: mkdocs ; extra == 'doc'
Requires-Dist: mkdocs-material ; extra == 'doc'
Requires-Dist: mkdocs-git-revision-date-localized-plugin ; extra == 'doc'
Requires-Dist: mkdocs-literate-nav ; extra == 'doc'
Requires-Dist: mkdocs-macros-plugin ; extra == 'doc'
Requires-Dist: mkdocs-macros-includex ; extra == 'doc'
Requires-Dist: mkdocs-exclude ; extra == 'doc'
Requires-Dist: mkdocs-autorefs ; extra == 'doc'
Requires-Dist: pyyaml ; extra == 'doc'
Provides-Extra: test
Requires-Dist: pytest ; extra == 'test'
Requires-Dist: pytest-venv ; extra == 'test'
Requires-Dist: pytest-xdist ; extra == 'test'
Requires-Dist: pexpect ; extra == 'test'
